odoo9_addon_product_attribute_priority-9.0.1.0.0.99.dev2-py2.7-nspkg.pth
odoo9_addon_product_attribute_priority-9.0.1.0.0.99.dev2.dist-info/DESCRIPTION.rst
odoo9_addon_product_attribute_priority-9.0.1.0.0.99.dev2.dist-info/METADATA
odoo9_addon_product_attribute_priority-9.0.1.0.0.99.dev2.dist-info/RECORD
odoo9_addon_product_attribute_priority-9.0.1.0.0.99.dev2.dist-info/WHEEL
odoo9_addon_product_attribute_priority-9.0.1.0.0.99.dev2.dist-info/metadata.json
odoo9_addon_product_attribute_priority-9.0.1.0.0.99.dev2.dist-info/namespace_packages.txt
odoo9_addon_product_attribute_priority-9.0.1.0.0.99.dev2.dist-info/top_level.txt
odoo_addons/product_attribute_priority/README.rst
odoo_addons/product_attribute_priority/__init__.py
odoo_addons/product_attribute_priority/__openerp__.py
odoo_addons/product_attribute_priority/i18n/product_attribute_priority.pot
odoo_addons/product_attribute_priority/models/__init__.py
odoo_addons/product_attribute_priority/models/product_attribute.py
odoo_addons/product_attribute_priority/models/product_attribute_line.py
odoo_addons/product_attribute_priority/models/product_attribute_value.py
odoo_addons/product_attribute_priority/static/description/icon.png
odoo_addons/product_attribute_priority/views/product_view.xml
