Metadata-Version: 2.0
Name: odoo9-addon-product-attribute-priority
Version: 9.0.1.0.0.99.dev2
Summary: Product attribute priority
Home-page: http://www.kmee.com.br
Author: KMEE INFORMATICA LTDA,Odoo Community Association (OCA)
Author-email: support@odoo-community.org
License: AGPL-3
Platform: UNKNOWN
Classifier: Programming Language :: Python
Classifier: Framework :: Odoo
Classifier: License :: OSI Approved :: GNU Affero General Public License v3
Requires-Python: ~=2.7
Requires-Dist: odoo (<9.1a,>=9.0a)
